src/Test/Test.py
src/Test/__init__.py
test_site-1.0.0.dist-info/METADATA
test_site-1.0.0.dist-info/WHEEL
test_site-1.0.0.dist-info/entry_points.txt
test_site-1.0.0.dist-info/licenses/LICENSE
test_site-1.0.0.dist-info/RECORD
