Metadata-Version: 2.4
Name: Test-site
Version: 1.0.0
Summary: test some small experiments
Project-URL: Repository, https://github.com/leo1oel/Test-site
Author-email: Yiming Liu <liuym23@mails.tsinghua.edu.cn>
License-Expression: MIT
License-File: LICENSE
Requires-Python: <4.0,>=3.11
